[{"name":"loBxHuY","marks":18},{"name":"3ApJYi","marks":41},{"name":"OdVAej","marks":48},{"name":"1","marks":99},{"name":"1iSWeY","marks":32},{"name":"KF","marks":4},{"name":"Qvnli2OP","marks":4},{"name":"nbn","marks":94},{"name":"vblS1","marks":94},{"name":"3u2wl8tJ","marks":72},{"name":"za","marks":99},{"name":"Ean3wV0kX","marks":29},{"name":"AdhLmVhTC","marks":65},{"name":"zdjwr8","marks":15},{"name":"iDI","marks":9},{"name":"XX","marks":80},{"name":"I7JvuDrZbO","marks":4},{"name":"76gohLPC","marks":52},{"name":"52WcVk5Cd","marks":87},{"name":"C1","marks":70},{"name":"uUn","marks":98},{"name":"2UzA5e","marks":84},{"name":"wYuPZ4Jm","marks":47},{"name":"v9W","marks":83},{"name":"Ym","marks":9},{"name":"Biyw","marks":91},{"name":"0nMxE","marks":0},{"name":"z876X","marks":67},{"name":"nnsTvDo","marks":26},{"name":"6","marks":5},{"name":"NJfS","marks":19},{"name":"HXLMb","marks":68},{"name":"YdCttbp","marks":74},{"name":"KVMQUFdN","marks":76},{"name":"NBjO","marks":63},{"name":"d","marks":66},{"name":"8UvcCsK","marks":18},{"name":"Hn6ZB2JMgY","marks":72},{"name":"5X5T7c","marks":1},{"name":"91Vu09xOZ","marks":84},{"name":"k","marks":19},{"name":"sM8","marks":1},{"name":"LZk","marks":76},{"name":"EGWf7eT","marks":44},{"name":"2","marks":82},{"name":"S7HMADcc","marks":88},{"name":"F66akWd1DS","marks":72},{"name":"57MvJBIoOR","marks":99},{"name":"aBLtc46","marks":61},{"name":"PA9","marks":50},{"name":"bP52","marks":63},{"name":"xgpHA5n","marks":84},{"name":"MZ","marks":28},{"name":"Ib4C9pYRra","marks":83},{"name":"0xEhmubo","marks":77},{"name":"sLxdjEsgF","marks":55},{"name":"04JeN","marks":92},{"name":"o5RBocNNn","marks":91},{"name":"bXS4ZlfpT","marks":94},{"name":"04rkIMTmLY","marks":99},{"name":"LeoMf","marks":39},{"name":"M","marks":31},{"name":"fD","marks":72},{"name":"tQyvHo","marks":56},{"name":"Y","marks":24},{"name":"pXhU","marks":23},{"name":"PR","marks":97},{"name":"t1Hn0bQWPW","marks":80},{"name":"psM","marks":16},{"name":"yDWWM78","marks":62},{"name":"0E","marks":98},{"name":"P7","marks":88},{"name":"TLaFetYCEZ","marks":34},{"name":"c1p0q","marks":76},{"name":"zxkYCC","marks":98},{"name":"HXmKjjD","marks":41},{"name":"YHvA","marks":62},{"name":"0OPCU","marks":40},{"name":"CThsI","marks":89},{"name":"Kcw1KVOGRy","marks":74},{"name":"dSNETGq","marks":38},{"name":"JL","marks":16},{"name":"IXo6e","marks":16},{"name":"PbIQ","marks":50},{"name":"LdZ","marks":27},{"name":"2KpoLT2Tv","marks":68},{"name":"AjeU4ikNDp","marks":44},{"name":"coRr3v","marks":61},{"name":"szorXmQ","marks":5},{"name":"CBFADFdf","marks":33},{"name":"C","marks":9},{"name":"vZBNUe","marks":35},{"name":"HJIn","marks":77},{"name":"NXao1Sk","marks":81},{"name":"1n","marks":55},{"name":"Ae","marks":46},{"name":"T","marks":34},{"name":"x7zF","marks":37},{"name":"Gpyg","marks":38},{"name":"R","marks":62}]
